bardeen/__init__.py
bardeen/array_combi.py
bardeen/code_style.py
bardeen/collection.py
bardeen/grid.py
bardeen/image.py
bardeen/inout.py
bardeen/npjson.py
bardeen/numerical.py
bardeen/parallel.py
bardeen/storage.py
bardeen/system.py
bardeen/testutils.py
bardeen/text.py
bardeen/to_be_included.py
bardeen/visualize.py
bardeen-1.4.2.dist-info/DESCRIPTION.rst
bardeen-1.4.2.dist-info/METADATA
bardeen-1.4.2.dist-info/RECORD
bardeen-1.4.2.dist-info/WHEEL
bardeen-1.4.2.dist-info/metadata.json
bardeen-1.4.2.dist-info/top_level.txt
